v2raysub/__init__.py
v2raysub/app.py
v2raysub/cli.py
v2raysub/config.py
v2raysub/protocol.py
v2raysub/service.py
v2raysub/util.py
v2raysub-0.3.2.dist-info/LICENSE
v2raysub-0.3.2.dist-info/METADATA
v2raysub-0.3.2.dist-info/WHEEL
v2raysub-0.3.2.dist-info/entry_points.txt
v2raysub-0.3.2.dist-info/top_level.txt
v2raysub-0.3.2.dist-info/RECORD
