Metadata-Version: 2.1
Name: v2raysub
Version: 0.3.2
Summary: subscription and config generation tool for v2ray
Home-page: https://github.com/12CrazyPaul21/v2raysub
Author: hzq
Author-email: 604916833@qq.com
License: Apache License, Version 2.0
Project-URL: Source, https://github.com/12CrazyPaul21/v2raysub
Keywords: v2ray,config,subscribe,proxy,proxychains
Classifier: Environment :: Console
Classifier: License :: OSI Approved :: Apache Software License
Classifier: Natural Language :: English
Classifier: Operating System :: MacOS :: MacOS X
Classifier: Operating System :: Microsoft :: Windows
Classifier: Operating System :: POSIX :: Linux
Classifier: Programming Language :: Python :: 3 :: Only
Classifier: Topic :: Software Development :: Build Tools
Requires-Python: >=3.8
License-File: LICENSE
Requires-Dist: requests
Requires-Dist: click
Requires-Dist: questionary
Requires-Dist: psutil
Requires-Dist: tqdm
Requires-Dist: pywin32; sys_platform == "win32"
Requires-Dist: pyinstaller; sys_platform == "win32"
